<?xml version="1.0"?>
<root>

  <vkchangeinputsourcedef>
    <name>KeyCode::VK_CHANGE_INPUTSOURCE_ARABIC</name>
    <languagecode>ar</languagecode>
  </vkchangeinputsourcedef>

  <vkchangeinputsourcedef>
    <name>KeyCode::VK_CHANGE_INPUTSOURCE_BELARUSIAN</name>
    <languagecode>be</languagecode>
  </vkchangeinputsourcedef>

  <vkchangeinputsourcedef>
    <name>KeyCode::VK_CHANGE_INPUTSOURCE_BELGIAN</name>
    <languagecode>nl</languagecode>
  </vkchangeinputsourcedef>

  <vkchangeinputsourcedef>
    <name>KeyCode::VK_CHANGE_INPUTSOURCE_BEPO</name>
    <inputsourceid_equal>com.apple.keyboardlayout.fr-dvorak-bepo.keylayout.FrenchDvorak</inputsourceid_equal>
  </vkchangeinputsourcedef>

  <vkchangeinputsourcedef>
    <name>KeyCode::VK_CHANGE_INPUTSOURCE_BEPO_AZERTYCMD</name>
    <inputsourceid_equal>com.apple.keyboardlayout.fr-dvorak-bepo.keylayout.FrenchDvorak-AzertyCmd</inputsourceid_equal>
  </vkchangeinputsourcedef>

  <vkchangeinputsourcedef>
    <name>KeyCode::VK_CHANGE_INPUTSOURCE_BEPO_AZERTYCMDROMAN</name>
    <inputsourceid_equal>com.apple.keyboardlayout.fr-dvorak-bepo.keylayout.FrenchDvorak-AzertyCmdRoman</inputsourceid_equal>
  </vkchangeinputsourcedef>

  <vkchangeinputsourcedef>
    <name>KeyCode::VK_CHANGE_INPUTSOURCE_BEPO_QWERTYCMD</name>
    <inputsourceid_equal>com.apple.keyboardlayout.fr-dvorak-bepo.keylayout.FrenchDvorak-QwertyCmd</inputsourceid_equal>
  </vkchangeinputsourcedef>

  <vkchangeinputsourcedef>
    <name>KeyCode::VK_CHANGE_INPUTSOURCE_BEPO_QWERTYCMDROMAN</name>
    <inputsourceid_equal>com.apple.keyboardlayout.fr-dvorak-bepo.keylayout.FrenchDvorak-QwertyCmdRoman</inputsourceid_equal>
  </vkchangeinputsourcedef>

  <vkchangeinputsourcedef>
    <name>KeyCode::VK_CHANGE_INPUTSOURCE_BEPO_QWERTZCMD</name>
    <inputsourceid_equal>com.apple.keyboardlayout.fr-dvorak-bepo.keylayout.FrenchDvorak-QwertzCmd</inputsourceid_equal>
  </vkchangeinputsourcedef>

  <vkchangeinputsourcedef>
    <name>KeyCode::VK_CHANGE_INPUTSOURCE_BEPO_QWERTZCMDROMAN</name>
    <inputsourceid_equal>com.apple.keyboardlayout.fr-dvorak-bepo.keylayout.FrenchDvorak-QwertzCmdRoman</inputsourceid_equal>
  </vkchangeinputsourcedef>

  <vkchangeinputsourcedef>
    <name>KeyCode::VK_CHANGE_INPUTSOURCE_BEPO_ROMAN</name>
    <inputsourceid_equal>com.apple.keyboardlayout.fr-dvorak-bepo.keylayout.FrenchDvorakRoman</inputsourceid_equal>
  </vkchangeinputsourcedef>

  <vkchangeinputsourcedef>
    <name>KeyCode::VK_CHANGE_INPUTSOURCE_BRITISH</name>
    <inputsourceid_prefix>com.apple.keylayout.British</inputsourceid_prefix>
  </vkchangeinputsourcedef>

  <vkchangeinputsourcedef>
    <name>KeyCode::VK_CHANGE_INPUTSOURCE_BRITISH_PC</name>
    <inputsourceid_equal>com.apple.keylayout.British-PC</inputsourceid_equal>
  </vkchangeinputsourcedef>

  <vkchangeinputsourcedef>
    <name>KeyCode::VK_CHANGE_INPUTSOURCE_BULGARIAN</name>
    <languagecode>bg</languagecode>
  </vkchangeinputsourcedef>

  <vkchangeinputsourcedef>
    <name>KeyCode::VK_CHANGE_INPUTSOURCE_CANADIAN</name>
    <inputsourceid_prefix>com.apple.keylayout.Canadian</inputsourceid_prefix>
  </vkchangeinputsourcedef>

  <!-- OS X might have a bug around Chinese input source switching.
       Please see comments of KeyCode::VK_CHANGE_INPUTSOURCE_JAPANESE. -->
  <vkchangeinputsourcedef>
    <name>KeyCode::VK_CHANGE_INPUTSOURCE_CHINESE_SIMPLIFIED</name>
    <inputmodeid_prefix>com.apple.inputmethod.SCIM</inputmodeid_prefix>
  </vkchangeinputsourcedef>

  <!-- OS X might have a bug around Chinese input source switching.
       Please see comments of KeyCode::VK_CHANGE_INPUTSOURCE_JAPANESE. -->
  <vkchangeinputsourcedef>
    <name>KeyCode::VK_CHANGE_INPUTSOURCE_CHINESE_TRADITIONAL</name>
    <inputmodeid_prefix>com.apple.inputmethod.TCIM</inputmodeid_prefix>
  </vkchangeinputsourcedef>

  <vkchangeinputsourcedef>
    <name>KeyCode::VK_CHANGE_INPUTSOURCE_COLEMAK</name>
    <inputsourceid_equal>com.apple.keylayout.Colemak</inputsourceid_equal>
  </vkchangeinputsourcedef>

  <vkchangeinputsourcedef>
    <name>KeyCode::VK_CHANGE_INPUTSOURCE_CROATIAN</name>
    <languagecode>hr</languagecode>
  </vkchangeinputsourcedef>

  <vkchangeinputsourcedef>
    <name>KeyCode::VK_CHANGE_INPUTSOURCE_CZECH</name>
    <languagecode>cs</languagecode>
  </vkchangeinputsourcedef>

  <vkchangeinputsourcedef>
    <name>KeyCode::VK_CHANGE_INPUTSOURCE_DANISH</name>
    <languagecode>da</languagecode>
  </vkchangeinputsourcedef>

  <vkchangeinputsourcedef>
    <name>KeyCode::VK_CHANGE_INPUTSOURCE_DVORAK</name>
    <inputsourceid_equal>com.apple.keylayout.Dvorak</inputsourceid_equal>
  </vkchangeinputsourcedef>

  <vkchangeinputsourcedef>
    <name>KeyCode::VK_CHANGE_INPUTSOURCE_DVORAK_DEVANAGARI_PAUL</name>
    <inputsourceid_equal>org.unknown.keylayout.DvorakDevanagariPaul</inputsourceid_equal>
  </vkchangeinputsourcedef>

  <vkchangeinputsourcedef>
    <name>KeyCode::VK_CHANGE_INPUTSOURCE_DVORAK_LEFT</name>
    <inputsourceid_equal>com.apple.keylayout.Dvorak-Left</inputsourceid_equal>
  </vkchangeinputsourcedef>

  <vkchangeinputsourcedef>
    <name>KeyCode::VK_CHANGE_INPUTSOURCE_DVORAK_QWERTYCMD</name>
    <inputsourceid_equal>com.apple.keylayout.DVORAK-QWERTYCMD</inputsourceid_equal>
  </vkchangeinputsourcedef>

  <vkchangeinputsourcedef>
    <name>KeyCode::VK_CHANGE_INPUTSOURCE_DVORAK_RIGHT</name>
    <inputsourceid_equal>com.apple.keylayout.Dvorak-Right</inputsourceid_equal>
  </vkchangeinputsourcedef>

  <vkchangeinputsourcedef>
    <name>KeyCode::VK_CHANGE_INPUTSOURCE_DVORAK_TRANSLIT_NEW</name>
    <inputsourceid_equal>org.unknown.keylayout.DvorakTranslitNew</inputsourceid_equal>
  </vkchangeinputsourcedef>

  <vkchangeinputsourcedef>
    <name>KeyCode::VK_CHANGE_INPUTSOURCE_ENGLISH</name>
    <languagecode>en</languagecode>
    <inputsourceid_equal>org.unknown.keylayout.English-IlyaBirmanTypography</inputsourceid_equal>
  </vkchangeinputsourcedef>

  <vkchangeinputsourcedef>
    <name>KeyCode::VK_CHANGE_INPUTSOURCE_ENGLISH_TYPOGRAPHIC</name>
    <inputsourceid_equal>org.sil.ukelele.keyboardlayout.t.english- ilya birman typography</inputsourceid_equal>
  </vkchangeinputsourcedef>

  <vkchangeinputsourcedef>
    <name>KeyCode::VK_CHANGE_INPUTSOURCE_ESTONIAN</name>
    <languagecode>et</languagecode>
  </vkchangeinputsourcedef>

  <vkchangeinputsourcedef>
    <name>KeyCode::VK_CHANGE_INPUTSOURCE_FINNISH</name>
    <languagecode>fi</languagecode>
  </vkchangeinputsourcedef>

  <vkchangeinputsourcedef>
    <name>KeyCode::VK_CHANGE_INPUTSOURCE_FRENCH</name>
    <languagecode>fr</languagecode>
  </vkchangeinputsourcedef>

  <vkchangeinputsourcedef>
    <name>KeyCode::VK_CHANGE_INPUTSOURCE_FRENCH_NUMERICAL</name>
    <inputsourceid_equal>com.apple.keylayout.French-numerical</inputsourceid_equal>
  </vkchangeinputsourcedef>

  <vkchangeinputsourcedef>
    <name>KeyCode::VK_CHANGE_INPUTSOURCE_GERMAN</name>
    <languagecode>de</languagecode>
  </vkchangeinputsourcedef>

  <vkchangeinputsourcedef>
    <name>KeyCode::VK_CHANGE_INPUTSOURCE_GREEK</name>
    <languagecode>el</languagecode>
  </vkchangeinputsourcedef>

  <vkchangeinputsourcedef>
    <name>KeyCode::VK_CHANGE_INPUTSOURCE_HEBREW</name>
    <languagecode>he</languagecode>
    <inputsourceid_equal>org.unknown.keylayout.Hebrew</inputsourceid_equal>
  </vkchangeinputsourcedef>

  <vkchangeinputsourcedef>
    <name>KeyCode::VK_CHANGE_INPUTSOURCE_HUNGARIAN</name>
    <languagecode>hu</languagecode>
  </vkchangeinputsourcedef>

  <vkchangeinputsourcedef>
    <name>KeyCode::VK_CHANGE_INPUTSOURCE_HUNGARIAN_PRO</name>
    <inputsourceid_equal>com.apple.keyboardlayout.unicode.keylayout.HungarianPRO</inputsourceid_equal>
  </vkchangeinputsourcedef>

  <vkchangeinputsourcedef>
    <name>KeyCode::VK_CHANGE_INPUTSOURCE_HUNGARIAN_PRO_PC</name>
    <inputsourceid_equal>com.apple.keyboardlayout.unicode.keylayout.HungarianPROPC</inputsourceid_equal>
  </vkchangeinputsourcedef>

  <vkchangeinputsourcedef>
    <name>KeyCode::VK_CHANGE_INPUTSOURCE_ITALIAN</name>
    <languagecode>it</languagecode>
  </vkchangeinputsourcedef>

  <!--
      | Note:
      | Sometimes the input source switching API (TISSelectInputSource) does not work properly for some input sources.
      | It changes an indicator (statusbar), but behavior of input source is not changed.
      |
      | For example, when we change input source to Japanese from U.S.,
      | the indicator is changed to Japanese.
      | But we cannot input Japanese. Our typing is interpreted as U.S.
      |
      | This issue is occurred on the input sources which has complex behavior such as Japanese.
      | If you faced this issue, use command-option-space (Select next source in Input menu)
      | instead of KeyCode::VK_CHANGE_INPUTSOURCE_JAPANESE like this.
      |
      | <autogen>
      |   __KeyToKey__
      |
      |   KeyCode::SHIFT_R,
      |
      |   KeyCode::VK_CHANGE_INPUTSOURCE_ENGLISH,
      |   KeyCode::VK_WAIT_100MS,
      |   KeyCode::SPACE, ModifierFlag::COMMAND_L | ModifierFlag::OPTION_L,
      | </autogen>
      |
      | This autogen changes input source to english (previous item of Japanese) and
      | waits until input source was changed to english.
      | Then send command-option-space in order to change input source to Japanese.
  -->
  <vkchangeinputsourcedef>
    <name>KeyCode::VK_CHANGE_INPUTSOURCE_JAPANESE</name>
    <languagecode>ja</languagecode>
  </vkchangeinputsourcedef>

  <!-- OS X might have a bug around Chinese input source switching.
       Please see comments of KeyCode::VK_CHANGE_INPUTSOURCE_JAPANESE. -->
  <vkchangeinputsourcedef>
    <name>KeyCode::VK_CHANGE_INPUTSOURCE_KOREAN</name>
    <inputmodeid_prefix>com.apple.inputmethod.Korean</inputmodeid_prefix>
  </vkchangeinputsourcedef>

  <vkchangeinputsourcedef>
    <name>KeyCode::VK_CHANGE_INPUTSOURCE_NORWEGIAN</name>
    <languagecode>nb</languagecode>
  </vkchangeinputsourcedef>

  <vkchangeinputsourcedef>
    <name>KeyCode::VK_CHANGE_INPUTSOURCE_POLISH</name>
    <languagecode>pl</languagecode>
  </vkchangeinputsourcedef>

  <vkchangeinputsourcedef>
    <name>KeyCode::VK_CHANGE_INPUTSOURCE_POLISH_PRO</name>
    <inputsourceid_equal>com.apple.keylayout.PolishPro</inputsourceid_equal>
  </vkchangeinputsourcedef>

  <vkchangeinputsourcedef>
    <name>KeyCode::VK_CHANGE_INPUTSOURCE_PORTUGUESE</name>
    <languagecode>pt</languagecode>
  </vkchangeinputsourcedef>

  <vkchangeinputsourcedef>
    <name>KeyCode::VK_CHANGE_INPUTSOURCE_RUSSIAN</name>
    <languagecode>ru</languagecode>
    <inputsourceid_equal>org.unknown.keylayout.RussianWin</inputsourceid_equal>
    <inputsourceid_equal>org.unknown.keylayout.Russian-IlyaBirmanTypography</inputsourceid_equal>
  </vkchangeinputsourcedef>

  <vkchangeinputsourcedef>
    <name>KeyCode::VK_CHANGE_INPUTSOURCE_RUSSIAN_TYPOGRAPHIC</name>
    <inputsourceid_equal>org.sil.ukelele.keyboardlayout.t.russian- ilya birman typography</inputsourceid_equal>
  </vkchangeinputsourcedef>

  <vkchangeinputsourcedef>
    <name>KeyCode::VK_CHANGE_INPUTSOURCE_SLOVENIAN</name>
    <languagecode>sl</languagecode>
  </vkchangeinputsourcedef>

  <vkchangeinputsourcedef>
    <name>KeyCode::VK_CHANGE_INPUTSOURCE_SPANISH</name>
    <languagecode>es</languagecode>
  </vkchangeinputsourcedef>

  <vkchangeinputsourcedef>
    <name>KeyCode::VK_CHANGE_INPUTSOURCE_SWEDISH</name>
    <languagecode>sv</languagecode>
  </vkchangeinputsourcedef>

  <vkchangeinputsourcedef>
    <name>KeyCode::VK_CHANGE_INPUTSOURCE_SWEDISH_PRO</name>
    <inputsourceid_equal>com.apple.keylayout.Swedish-Pro</inputsourceid_equal>
  </vkchangeinputsourcedef>

  <vkchangeinputsourcedef>
    <name>KeyCode::VK_CHANGE_INPUTSOURCE_SWISS</name>
    <inputsourceid_prefix>com.apple.keylayout.Swiss</inputsourceid_prefix>
  </vkchangeinputsourcedef>

  <vkchangeinputsourcedef>
    <name>KeyCode::VK_CHANGE_INPUTSOURCE_SWISS_GERMAN</name>
    <inputsourceid_equal>com.apple.keylayout.SwissGerman</inputsourceid_equal>
  </vkchangeinputsourcedef>

  <vkchangeinputsourcedef>
    <name>KeyCode::VK_CHANGE_INPUTSOURCE_THAI</name>
    <languagecode>th</languagecode>
  </vkchangeinputsourcedef>

  <!-- OS X might have a bug around Chinese input source switching.
       Please see comments of KeyCode::VK_CHANGE_INPUTSOURCE_JAPANESE. -->
  <vkchangeinputsourcedef>
    <name>KeyCode::VK_CHANGE_INPUTSOURCE_TRADITIONAL_CHINESE_YAHOO_KEYKEY</name>
    <inputsourceid_equal>com.yahoo.inputmethod.KeyKey</inputsourceid_equal>
  </vkchangeinputsourcedef>

  <vkchangeinputsourcedef>
    <name>KeyCode::VK_CHANGE_INPUTSOURCE_UKRAINIAN</name>
    <languagecode>uk</languagecode>
  </vkchangeinputsourcedef>

  <!-- A popular UKRAINIAN PC layout from http://bluezbox.com/uapc.html -->
  <vkchangeinputsourcedef>
    <name>KeyCode::VK_CHANGE_INPUTSOURCE_UKRAINIAN_PC</name>
    <inputsourceid_equal>org.unknown.keylayout.Ukrainian-PC</inputsourceid_equal>
  </vkchangeinputsourcedef>

  <vkchangeinputsourcedef>
    <name>KeyCode::VK_CHANGE_INPUTSOURCE_UNICODEHEXINPUT</name>
    <inputsourceid_equal>com.apple.keylayout.UnicodeHexInput</inputsourceid_equal>
  </vkchangeinputsourcedef>

  <vkchangeinputsourcedef>
    <name>KeyCode::VK_CHANGE_INPUTSOURCE_US</name>
    <inputsourceid_equal>com.apple.keylayout.US</inputsourceid_equal>
  </vkchangeinputsourcedef>

</root>
